hypermodern_pc/__init__.py
hypermodern_pc/console.py
hypermodern_pc/wikipedia.py
hypermodern_pc-0.1.1.dist-info/LICENSE
hypermodern_pc-0.1.1.dist-info/METADATA
hypermodern_pc-0.1.1.dist-info/WHEEL
hypermodern_pc-0.1.1.dist-info/entry_points.txt
hypermodern_pc-0.1.1.dist-info/RECORD
